{
  "type": [
    "null",
    "object"
  ],
  "properties": {
    "id": {
      "type": [
        "null",
        "string"
      ]
    },
    "object": {
      "type": [
        "null",
        "string"
      ]
    },
    "plan_id": {
      "type": [
        "null",
        "string"
      ]
    },
    "code": {
      "type": [
        "null",
        "string"
      ]
    },
    "state": {
      "type": [
        "null",
        "string"
      ]
    },
    "name": {
      "type": [
        "null",
        "string"
      ]
    },
    "add_on_type": {
      "type": [
        "null",
        "string"
      ]
    },
    "usage_type": {
      "type": [
        "null",
        "string"
      ]
    },
    "usage_percentage": {
      "type": [
        "null",
        "number"
      ]
    },
    "measured_unit_id": {
      "type": [
        "null",
        "string"
      ]
    },
    "display_quantity": {
      "type": [
        "null",
        "boolean"
      ]
    },
    "default_quantity": {
      "type": [
        "null",
        "integer"
      ]
    },
    "accounting_code": {
      "type": [
        "null",
        "string"
      ]
    },
    "tax_code": {
      "type": [
        "null",
        "string"
      ]
    },
    "revenue_schedule_type": {
      "type": [
        "null",
        "string"
      ]
    },
    "optional": {
      "type": [
        "null",
        "boolean"
      ]
    },
    "currencies": {
      "type": [
        "null",
        "array"
      ],
      "items": {
        "type": [
          "null",
          "object"
        ],
        "properties": {
          "currency": {
            "type": [
              "null",
              "string"
            ]
          },
          "unit_amount": {
            "type": [
              "null",
              "number"
            ]
          },
          "unit_amount_decimal": {
            "type": [
              "null"
            ]
          }
        }
      }
    },
    "usage_timeframe": {
      "type": [
        "null",
        "string"
      ]
    },
    "usage_calculation_type": {
      "type": [
        "null",
        "string"
      ]
    },
    "tier_type": {
      "type": [
        "null",
        "string"
      ]
    },
    "item": {
      "type": [
        "null"
      ]
    },
    "external_sku": {
      "type": [
        "null"
      ]
    },
    "created_at": {
      "type": [
        "null",
        "string"
      ]
    },
    "updated_at": {
      "type": [
        "null",
        "string"
      ]
    },
    "deleted_at": {
      "type": [
        "null"
      ]
    }
  }
}
